{
  "Ciék-káik": "République tchèque",
  "Hò̤-làng": "Pays-Bas",
  "Dâi-iòng-ciŭ": "Océanie",
  "Hĭ-ciŭ": "Afrique",
  "Vaticano": "Vatican",
  "San Marino": "Saint-Marin",
  "Luxembourg": "Luxembourg (pays)",
  "Dáik-guók": "Allemagne",
  "Andorra": "Andorre",
  "Éng-dô-iòng": "Océan Indien",
  "Slovakia": "Slovaquie",
  "Ùng-huá": "Culture",
  "Cṳ̆-buōng-ciō-ngiê": "Capitalisme",
  "É-dâi-lé": "Italie",
  "Ó̤-dê-lé": "Autriche",
  "Nàng-bĭng-iòng": "Océan Austral",
  "Bĭng-dō̤": "Islande",
  "Belarus": "Biélorussie",
  "Ĭng-guók": "Royaume-Uni",
  "Sôi-diēng": "Suède",
  "Guók-gă": "Pays",
  "Ā-ciŭ": "Asie",
  "Báe̤k-bĭng-iòng": "Océan Arctique",
  "Nàng Mī-ciŭ": "Amérique du Sud",
  "Să̤-băng-ngà": "Espagne",
  "Montenegro": "Monténégro",
  "Nò̤-ŭi": "Norvège",
  "Dâi-să̤-iòng": "Océan Atlantique",
  "Slovenia": "Slovénie",
  "Ĭng-ngṳ̄": "Anglais",
  "Armenia": "Arménie",
  "Georgia (guók-gă)": "Géorgie (pays)",
  "Tū-ī-gì": "Turquie",
  "Báe̤k Mī-ciŭ": "Amérique du Nord",
  "Kazakhstan": "Kazakhstan",
  "Ngò̤-lò̤-sṳ̆": "Russie",
  "Può-dò̤-ngà": "Portugal",
  "Ukraine": "Ukraine",
  "Dăng-măk": "Danemark",
  "Siâ-huôi-ciō-ngiê": "Socialisme",
  "Hŭng-làng": "Finlande",
  "Ái-ī-làng": "Irlande (pays)",
  "Sô̤i-sê̤ṳ": "Suisse",
  "Lithuania": "Lituanie",
  "Bī-lé-sì": "Belgique",
  "Moldova": "Moldavie",
  "Liechtenstein": "Liechtenstein",
  "Albania": "Albanie",
  "Croatia": "Croatie",
  "Malta": "Malte",
  "Monaco": "Monaco",
  "Sŭ-lièng": "Union des républiques socialistes soviétiques",
  "Hĭ-lé-nà̤-ngṳ̄": "Grec",
  "Huák-guók": "France",
  "Romania": "Roumanie",
  "Greenland": "Groenland",
  "Nàng-gĭk-ciŭ": "Antarctique",
  "Estonia": "Estonie",
  "Kosovo": "Kosovo",
  "Mī-ciŭ": "Amérique",
  "Serbia": "Serbie",
  "Azerbaijan": "Azerbaïdjan",
  "Gū Lò̤-mā": "Rome antique",
  "Pŏ̤-làng": "Pologne",
  "Tái-bìng-iòng": "Océan Pacifique",
  "Gĭ-dók-gáu": "Christianisme",
  "Latvia": "Lettonie",
  "Gū Hĭ-lé-nà̤": "Grèce antique",
  "Hungary": "Hongrie",
  "Nè̤ng": "Homo sapiens",
  "Hĭ-lé-nà̤": "Grèce",
  "Cyprus": "Chypre (pays)",
  "Bulgaria": "Bulgarie"
}