{
  "Jeremy Bentham": "Jeremy Bentham",
  "Process philosophy": "Philosophie du processus",
  "Nominalism": "Nominalisme",
  "Ethics of care": "Care (sciences sociales)",
  "Ilm al-Kalam": "Kalâm",
  "Western philosophy": "Philosophie occidentale",
  "Martha Nussbaum": "Martha Nussbaum",
  "Bioethics": "Bioéthique",
  "Autonomy": "Autonomie",
  "Temporoparietal junction": "Carrefour temporo-pariétal",
  "Crime": "Crime",
  "Platonism": "Platonisme (doctrine philosophique)",
  "Religion": "Religion",
  "Postmodern philosophy": "Philosophie postmoderne",
  "Vampire bat": "Desmodontinae",
  "Egalitarianism": "Égalitarisme",
  "Index of philosophy": "Philosopher",
  "Gregory S. Paul": "Gregory S. Paul",
  "Neoplatonism": "Néoplatonisme",
  "Zoroastrianism": "Zoroastrisme",
  "Baruch Spinoza": "Baruch Spinoza",
  "Buddhist philosophy": "Philosophie bouddhiste",
  "Thomas Nagel": "Thomas Nagel",
  "Plato": "Platon",
  "Formalism (art)": "Formalisme",
  "Evil": "Mal",
  "Outline of academic disciplines": "Liste des disciplines scientifiques",
  "Tanakh": "Tanakh",
  "Digital object identifier": "Digital Object Identifier",
  "Kokugaku": "Kokugaku",
  "Sociobiology": "Sociobiologie",
  "Philosophy of history": "Philosophie de l'histoire",
  "Ethics": "Éthique",
  "Normative ethics": "Éthique normative",
  "Constructivist epistemology": "Constructivisme (épistémologie)",
  "Critical theory": "Théorie critique",
  "Averroism": "Averroïsme",
  "Code of conduct": "Code de conduite (entreprise)",
  "Judaism": "Judaïsme",
  "Sociocultural evolution": "Évolution socioculturelle",
  "Fons Trompenaars": "Fons Trompenaars",
  "The God Delusion": "Pour en finir avec Dieu",
  "Moral nihilism": "Amoralisme",
  "Dvaita": "Dvaita",
  "Lawrence Kohlberg": "Lawrence Kohlberg",
  "Apologetics": "Apologétique",
  "Political philosophy": "Philosophie politique",
  "Mohism": "Moïsme",
  "Group selection": "Sélection de groupe",
  "Deconstruction": "Déconstruction",
  "Søren Kierkegaard": "Søren Kierkegaard",
  "Philosophical anthropology": "Anthropologie philosophique",
  "Philippa Foot": "Philippa Foot",
  "Epicureanism": "Épicurisme",
  "Aesthetics": "Esthétique",
  "Charles Taylor (philosopher)": "Charles Taylor (philosophe)",
  "Virtue ethics": "Éthique de la vertu",
  "Discourse ethics": "Éthique de la discussion",
  "Ancient philosophy": "Philosophie antique",
  "Compatibilism": "Compatibilisme",
  "Buddhism": "Bouddhisme",
  "Lists of philosophers": "Liste de philosophes par année de naissance",
  "Sympathy": "Sympathie",
  "Moral panic": "Panique morale",
  "Alasdair MacIntyre": "Alasdair MacIntyre",
  "Casuistry": "Casuistique",
  "G. E. Moore": "George Edward Moore",
  "Secular ethics": "Éthique laïque",
  "Christian philosophy": "Philosophie chrétienne",
  "Scholasticism": "Scolastique",
  "Sigmund Freud": "Sigmund Freud",
  "Pythagoreanism": "École pythagoricienne",
  "Criminology": "Criminologie",
  "Idealism": "Idéalisme (philosophie)",
  "Epistemology": "Épistémologie",
  "Antony Flew": "Antony Flew",
  "Atomism": "Atomisme",
  "Renaissance humanism": "Humanisme de la Renaissance",
  "Amorality": "Amoralité",
  "Evolutionary biology": "Biologie de l'évolution",
  "Philosophy of physics": "Philosophie de la physique",
  "Mozi": "Mozi",
  "Pantheism": "Panthéisme",
  "Empiricism": "Empirisme",
  "Christianity": "Christianisme",
  "Divine command theory": "Théorie du commandement divin",
  "Agnosticism": "Agnosticisme",
  "Anarchism": "Anarchisme",
  "Id, ego and super-ego": "Seconde topique",
  "Zurvanism": "Zervanisme",
  "Synonym": "Synonymie",
  "Philosophy of biology": "Philosophie de la biologie",
  "Robert D. Putnam": "Robert Putnam",
  "Bernard Williams": "Bernard Williams",
  "History of philosophy": "Histoire de la philosophie",
  "Peter Singer": "Peter Singer",
  "Latin": "Latin",
  "Pre-Socratic philosophy": "Présocratiques",
  "Old Testament": "Ancien Testament",
  "Action theory (philosophy)": "Philosophie de l'action",
  "Kyoto School": "École de Kyoto",
  "Friedrich Nietzsche": "Friedrich Nietzsche",
  "Freethought": "Libre-pensée",
  "Monotheism": "Monothéisme",
  "Philosophy of technology": "Philosophie de la technique",
  "Virtue": "Vertu",
  "French philosophy": "Histoire de la philosophie française",
  "List of Russian philosophers": "Liste des philosophes russes",
  "Moral realism": "Réalisme moral",
  "Sex differences in psychology": "Différences de genre en psychologie humaine",
  "Simon Blackburn": "Simon Blackburn",
  "Inclusive fitness": "Valeur sélective inclusive",
  "Philosophy of space and time": "Philosophie de l'espace et du temps",
  "Japanese philosophy": "Philosophie japonaise",
  "Objectivism (Ayn Rand)": "Objectivisme (Ayn Rand)",
  "Environmental ethics": "Éthique de l'environnement",
  "Aristotle": "Aristote",
  "American philosophy": "Philosophie américaine",
  "Georg Wilhelm Friedrich Hegel": "Georg Wilhelm Friedrich Hegel",
  "Abortion": "Avortement",
  "Ordinary language philosophy": "Philosophie du langage ordinaire",
  "Meta-ethics": "Méta-éthique",
  "Atheism": "Athéisme",
  "Sweden": "Suède",
  "PubMed": "PubMed",
  "Reality": "Réalité",
  "Principle": "Principe (philosophie)",
  "Philosophy of culture": "Philosophie de la culture",
  "Ancient Greek philosophy": "Philosophie en Grèce antique",
  "Frankfurt School": "École de Francfort",
  "Richard Dawkins": "Richard Dawkins",
  "Xuanxue": "Xuanxue",
  "Arthur Schopenhauer": "Arthur Schopenhauer",
  "Concept": "Concept",
  "Theory of mind": "Théorie de l'esprit",
  "Legalism (Chinese philosophy)": "Légisme",
  "G. E. M. Anscombe": "G. E. M. Anscombe",
  "Mores": "Mœurs",
  "Peripatetic school": "École péripatétique",
  "International Standard Serial Number": "International Standard Serial Number",
  "Falsifiability": "Réfutabilité",
  "Applied ethics": "Éthique appliquée",
  "Metaphysics": "Métaphysique",
  "The Immoralist": "L'Immoraliste",
  "Legal positivism": "Positivisme juridique",
  "Cistercians": "Ordre cistercien",
  "Conservatism": "Conservatisme",
  "Philosophy of information": "Philosophie de l'information",
  "Psychoanalysis": "Psychanalyse",
  "Medieval philosophy": "Philosophie médiévale",
  "Happiness": "Bonheur",
  "Jonathan Haidt": "Jonathan Haidt",
  "Conscience": "Conscience",
  "Macmillan Publishers": "Macmillan Publishers",
  "Philosophy": "Philosophie",
  "Augustine of Hippo": "Augustin d'Hippone",
  "Cārvāka": "Chârvâka",
  "List of philosophies": "Liste des théories philosophiques",
  "Justice": "Justice",
  "Divorce": "Divorce",
  "Maternal bond": "Amour maternel",
  "Social constructionism": "Constructivisme social",
  "History of ethics": "Histoire de l'éthique",
  "Modernism": "Modernisme",
  "Illuminationism": "Sohrawardi",
  "Proceedings of the National Academy of Sciences of the United States of America": "Proceedings of the National Academy of Sciences",
  "Eastern philosophy": "Philosophie orientale",
  "Reciprocal altruism": "Altruisme réciproque",
  "Value (personal and cultural)": "Valeurs (sociologie)",
  "Behavioural genetics": "Génétique comportementale",
  "Descriptive ethics": "Éthique descriptive",
  "Rationalism": "Rationalisme",
  "Philosophy of religion": "Philosophie de la religion",
  "Kin selection": "Sélection de parentèle",
  "Empathy": "Empathie",
  "Sufi philosophy": "Philosophie soufie",
  "Evolutionary psychology": "Psychologie évolutionniste",
  "Feminist philosophy": "Philosophie féministe",
  "Michael Shermer": "Michael Shermer",
  "Belief": "Croyance",
  "Tintoretto": "Le Tintoret",
  "International Standard Book Number": "International Standard Book Number",
  "Existentialism": "Existentialisme",
  "Jean Piaget": "Jean Piaget",
  "Mazdak": "Mazdakisme",
  "Consequentialism": "Conséquentialisme",
  "Utilitarianism": "Utilitarisme",
  "Suffering": "Souffrance",
  "Princeton University Press": "Princeton University Press",
  "Ontology": "Ontologie (philosophie)",
  "United States": "États-Unis",
  "Analytic philosophy": "Philosophie analytique",
  "Xunzi": "Xun Zi",
  "Halakha": "Halakha",
  "Aristotelianism": "Aristotélisme",
  "Ingroups and outgroups": "Ingroup",
  "Bible": "Bible",
  "Avicenna": "Avicenne",
  "John Rawls": "John Rawls",
  "Denmark": "Danemark",
  "Confucius": "Confucius",
  "Neo-Confucianism": "Néoconfucianisme",
  "Biological specificity": "Conspécificité",
  "New Testament": "Nouveau Testament",
  "Ethology": "Éthologie",
  "Patricia Churchland": "Patricia Churchland",
  "David Hume": "David Hume",
  "Vishishtadvaita": "Vishishtâdvaita",
  "Business ethics": "Éthique des affaires",
  "Determinism": "Déterminisme",
  "Patriotism": "Patriotisme",
  "Immanuel Kant": "Emmanuel Kant",
  "Mirror neuron": "Neurone miroir",
  "Quietism (philosophy)": "Quiétisme",
  "Post-structuralism": "Post-structuralisme",
  "Neo-Kantianism": "Néokantisme",
  "Chinese philosophy": "Philosophie chinoise",
  "Psychopathy": "Psychopathie",
  "Internalism and externalism": "Externalisme",
  "Cartesianism": "Cartésianisme",
  "Philosophy of mind": "Philosophie de l'esprit",
  "Derek Parfit": "Derek Parfit",
  "Conceptualism": "Conceptualisme",
  "Stoicism": "Stoïcisme",
  "Noam Chomsky": "Noam Chomsky",
  "Prosocial behavior": "Comportement prosocial",
  "Philosophy and economics": "Philosophie économique",
  "Eusociality": "Eusocialité",
  "Georges Chapouthier": "Georges Chapouthier",
  "Ludwig Wittgenstein": "Ludwig Wittgenstein",
  "Continental philosophy": "Philosophie continentale",
  "Modern philosophy": "Philosophie moderne",
  "Nationalism": "Nationalisme",
  "Glossary of philosophy": "Glossaire de philosophie",
  "Cynicism (philosophy)": "Cynisme",
  "Structuralism": "Structuralisme",
  "Eliminative materialism": "Éliminativisme",
  "Hellenistic philosophy": "Philosophie hellénistique",
  "Cooperation": "Coopération (économie sociale)",
  "Jurisprudence": "Philosophie du droit",
  "University of Michigan": "Université du Michigan",
  "Thomas Aquinas": "Thomas d'Aquin",
  "Vienna Circle": "Cercle de Vienne",
  "Experimental philosophy": "Philosophie expérimentale",
  "Transcendentalism": "Transcendantalisme (États-Unis)",
  "Book of Exodus": "Livre de l'Exode",
  "Pragmatism": "Pragmatisme",
  "Social philosophy": "Philosophie sociale",
  "Slavery": "Esclavage",
  "Islamic philosophy": "Philosophie islamique",
  "Free will": "Libre arbitre",
  "German philosophy": "Philosophie allemande",
  "Social psychology": "Psychologie sociale",
  "Westermarck effect": "Effet Westermarck",
  "Paul Tillich": "Paul Tillich",
  "Monism": "Monisme",
  "Foundationalism": "Fondationnalisme",
  "Lawrence Kohlberg's stages of moral development": "Théorie du développement moral de Kohlberg",
  "Logical positivism": "Empirisme logique",
  "Naturalism (philosophy)": "Naturalisme (philosophie)",
  "Event (philosophy)": "Événement (histoire)",
  "Categorical imperative": "Impératif catégorique",
  "Relativism": "Relativisme",
  "Empress Dowager Cixi": "Cixi",
  "John Stuart Mill": "John Stuart Mill",
  "Philosophy of science": "Philosophie des sciences",
  "The Moral Landscape": "The Moral Landscape: How Science Can Determine Human Values",
  "Solipsism": "Solipsisme",
  "School of Naturalists": "École du Yin-Yang",
  "Fideism": "Fidéisme",
  "Dietrich Bonhoeffer": "Dietrich Bonhoeffer",
  "Jewish ethics": "Moussar",
  "Philosophy of language": "Philosophie du langage",
  "Culture": "Culture",
  "Hermeneutics": "Herméneutique",
  "Karl Barth": "Karl Barth",
  "Golden Rule": "Éthique de réciprocité",
  "Political freedom": "Liberté (politique)",
  "African philosophy": "Philosophie africaine",
  "Altruism": "Altruisme",
  "Sam Harris (author)": "Sam Harris",
  "Philosophy of education": "Philosophie de l'éducation",
  "Cicero": "Cicéron",
  "Humanism": "Humanisme",
  "Convention (norm)": "Convention (droit)",
  "Thomism": "Thomisme",
  "Philosophical realism": "Réalisme (philosophie)",
  "Philosophy of computer science": "Épistémologie de l'informatique",
  "Good": "Good",
  "Absolute idealism": "Idéalisme absolu",
  "Transcranial magnetic stimulation": "Stimulation magnétique transcrânienne",
  "Islam": "Islam",
  "Logic": "Logique",
  "Behaviorism": "Comportementalisme",
  "Deontological ethics": "Éthique déontologique",
  "Vietnamese philosophy": "Philosophie vietnamienne",
  "Conformity": "Conformisme",
  "Murder": "Assassinat",
  "Sikhism": "Sikhisme",
  "Hinduism": "Hindouisme",
  "Axiology": "Axiologie",
  "Norm (social)": "Norme sociale",
  "Contemporary philosophy": "Philosophie contemporaine",
  "Philosophy of mathematics": "Philosophie des mathématiques",
  "Incest taboo": "Prohibition de l'inceste",
  "Objectivity (philosophy)": "Objectivité",
  "Appeal to tradition": "Argumentum ad antiquitatem",
  "Zen": "Zen",
  "Classical liberalism": "Libéralisme",
  "Jewish philosophy": "Philosophie juive",
  "Port": "Port",
  "Correlation and dependence": "Corrélation (statistiques)",
  "Indian philosophy": "Philosophie indienne",
  "Trust (social sciences)": "Confiance",
  "Reputation": "Réputation",
  "Materialism": "Matérialisme",
  "Proper": "Propre",
  "Henry Sidgwick": "Henry Sidgwick",
  "Mencius": "Mencius",
  "Confucianism": "Confucianisme",
  "Hominidae": "Hominidae",
  "Liberalism": "Libéralisme",
  "Taoism": "Taoïsme"
}