{
  "Turkey": "టర్కీ",
  "White House": "శ్వేత సౌధం",
  "Pierre Curie": "పియరీ క్యూరీ",
  "Solar eclipse": "సూర్య గ్రహణం",
  "Stephen Hawking": "స్టీఫెన్ హాకింగ్",
  "BBC": "బ్రిటిష్‌ బ్రాడ్‌కాస్టింగ్‌ కార్పొరేషన్‌",
  "Periodic table": "ఆవర్తన పట్టిక",
  "Theory of relativity": "సాపేక్ష సిద్ధాంతం",
  "Gravity": "గురుత్వాకర్షణ",
  "James Chadwick": "జేమ్స్ చాడ్విక్",
  "Quantum mechanics": "క్వాంటం యాంత్రిక శాస్త్రం",
  "Big Bang": "మహా విస్ఫోటం",
  "Plato": "ప్లేటో",
  "Alchemy": "రసవాదం",
  "Pragmatism": "వ్యావహారికసత్తావాదం",
  "Philosophy of perception": "ఇంద్రియజ్ఞాన తత్వ శాస్త్రం",
  "Astrophysics": "ఖగోళ భౌతిక శాస్త్రం",
  "Determinism": "డిటర్మినిజం",
  "Free fall": "స్వేచ్ఛా పతనం",
  "Momentum": "ద్రవ్యవేగం",
  "Violin": "వయొలిన్",
  "Scarlet fever": "స్కార్లెట్ జ్వరం",
  "Nicolaus Copernicus": "నికోలాస్ కోపర్నికస్",
  "Malaria": "మలేరియా",
  "Max Planck": "మాక్స్ ప్లాంక్",
  "Special relativity": "స్పెషల్ రెలెటివిటి",
  "Philosophy": "తత్వము",
  "YouTube": "యూ ట్యూబ్",
  "Bertrand Russell": "బెర్ట్రాండ్ రస్సెల్",
  "Berlin": "బెర్లిన్",
  "Black hole": "కృష్ణబిలం",
  "Enrico Fermi": "ఎన్ రికో ఫెర్మి",
  "Time (magazine)": "టైమ్ పత్రిక)",
  "Atom": "అణువు",
  "Galileo Galilei": "గెలీలియో గెలీలి",
  "Niels Bohr": "నీల్స్‌ బోర్",
  "Classical mechanics": "సాంప్రదాయ యాంత్రికశాస్త్రం",
  "Marie Curie": "మేరీ క్యూరీ",
  "Subrahmanyan Chandrasekhar": "సుబ్రహ్మణ్య చంద్రశేఖర్",
  "C. V. Raman": "చంద్రశేఖర వేంకట రామన్",
  "Laser": "లేజర్",
  "Avicenna": "ఇబ్నె సీనా",
  "Universe": "విశ్వం",
  "Satyendra Nath Bose": "సత్యేంద్రనాథ్ బోస్",
  "Dmitri Mendeleev": "మెండలీఫ్",
  "United States": "అమెరికా సంయుక్త రాష్ట్రాలు",
  "Matter": "పదార్థము",
  "Dark energy": "డార్క్ ఎనర్జీ",
  "Space": "అంతరిక్షం",
  "Ernest Rutherford": "ఎర్నెస్ట్ రూథర్‌ఫోర్డ్",
  "Japan": "జపాన్",
  "Switzerland": "స్విట్జర్లాండ్",
  "Electrical engineering": "ఎలక్ట్రికల్ ఇంజనీరింగ్",
  "Charlie Chaplin": "చార్లీ చాప్లిన్",
  "Physics": "భౌతిక శాస్త్రము",
  "Jawaharlal Nehru": "జవాహర్ లాల్ నెహ్రూ",
  "Princeton University": "ప్రిన్స్‌టన్ విశ్వవిద్యాలయం",
  "Atheism": "నాస్తికులు",
  "Isaac Newton": "ఐజాక్ న్యూటన్",
  "University of Oxford": "ఆక్స్‌ఫర్డ్ విశ్వవిద్యాలయం",
  "Royal Society": "రాయల్ సొసైటీ",
  "Photon": "ఫోటాన్",
  "Franklin D. Roosevelt": "ఫ్రాంక్లిన్ డి. రూజ్‌వెల్ట్",
  "Sigmund Freud": "సిగ్మండ్ ఫ్రాయిడ్",
  "Cousin marriage": "మేనరికం",
  "Singapore": "సింగపూరు",
  "Nobel Prize": "నోబెల్ బహుమతి",
  "Dark matter": "కృష్ణ పదార్థం",
  "Austria": "ఆస్ట్రియా",
  "Immanuel Kant": "ఇమ్మాన్యుయెల్ కాంట్",
  "Milan": "మిలన్",
  "Aristotle": "అరిస్టాటిల్",
  "Sri Lanka": "శ్రీలంక",
  "Adolf Hitler": "ఎడాల్ఫ్ హిట్లర్",
  "Pyotr Kapitsa": "ప్యోతర్ కపిత్సా",
  "Schizophrenia": "స్కిజోఫ్రీనియా",
  "Wilhelm Röntgen": "విల్హేల్మ్ కన్రాడ్ రాంట్జెన్",
  "Herbert Spencer": "హెర్బర్ట్ స్పెన్సర్",
  "Albert Einstein": "ఆల్బర్ట్ ఐన్‌స్టీన్",
  "Rabindranath Tagore": "రవీంద్రనాధ టాగూరు"
}