{
  "Knowledge": "Knowledge",
  "Moksha": "Moksha",
  "Plato": "Plato",
  "Digital object identifier": "Digital Object Identifier",
  "Benjamin Franklin": "Benjamin Franklin",
  "Dhammapada": "Dhammapada",
  "Hebrew Bible": "Hebrew Bible",
  "Newton's law of universal gravitation": "Newton's law of universal gravitation",
  "Psalms": "Psalms",
  "Limbic system": "Limbic system",
  "Science fiction": "Science fiction",
  "Socrates": "Socrates",
  "Christian theology": "Christian theology",
  "Carl Linnaeus": "Carolus Linnaeus",
  "Gautama Buddha": "Gautama Buddha",
  "Mencius": "Mencius",
  "Ganesha": "Ganesha",
  "Antidote": "Antidote",
  "Saraswati": "Saraswati",
  "Aristotle": "Aristotle",
  "PubMed Central": "PubMed Central",
  "Species": "Species",
  "Turkey": "Turkey",
  "First Epistle to the Corinthians": "First Epistle to the Corinthians",
  "Christianity": "Christianity",
  "Common sense": "Common sense",
  "Wisdom literature": "Wisdom literature",
  "Paul the Apostle": "Paul the Apostle",
  "Metis (mythology)": "Metis",
  "Artificial intelligence": "Artificial intelligence",
  "Latin": "Latin",
  "Quran": "Qur'an",
  "Wisdom": "Wisdom",
  "Book of Wisdom": "Book of Wisdom",
  "Ephesus": "Ephesus",
  "Verb": "Verb",
  "Virtue": "Virtue",
  "Odin": "Odin",
  "Jötunn": "Jötnar",
  "Utopia": "Utopia",
  "PubMed": "PubMed",
  "Norse mythology": "Norse mythology",
  "Consciousness": "Consciousness",
  "Mímir": "Mímir",
  "Intelligence": "Intelligence",
  "Insight": "Insight",
  "Jesus": "Jesus",
  "Human": "Human",
  "Talmud": "Talmud",
  "Philosophy": "Philosophy",
  "Causality": "Causality",
  "Psychology": "Psychology",
  "Runes": "Runes",
  "Catholicism": "Catholicism",
  "Tetragrammaton": "YHWH",
  "Poison": "Poison",
  "Buddhism": "Buddhism",
  "Legendary creature": "Legendary creature",
  "Minerva": "Minerva",
  "International Standard Book Number": "International Standard Book Number",
  "Æsir": "Æsir",
  "Anthropomorphism": "Anthropomorphism",
  "Inuit": "Inuit",
  "Confucius": "Confucius",
  "Extraterrestrial life": "Extraterrestrial life",
  "Experience": "Experience",
  "Theology": "Theology",
  "Dharma": "Dharma",
  "Academia": "Academia",
  "Ancient Rome": "Ancient Rome",
  "Binomial nomenclature": "Binomial nomenclature",
  "Greek language": "Greek language",
  "Wisdom in Buddhism": "Prajna",
  "Wise old man": "Sage",
  "Yggdrasil": "Yggdrasil",
  "Charles Spurgeon": "Charles Spurgeon",
  "Sentience": "Sentience",
  "Thomas Aquinas": "Thomas Aquinas",
  "God": "God",
  "Analogy": "Analogy",
  "Memory": "Memory",
  "Athena": "Athena",
  "Dialogue": "Dialogue",
  "Hebrew language": "Hebrew language",
  "The Republic (Plato)": "The Republic",
  "Proverb": "Proverb",
  "Book of Proverbs": "Book of Proverbs",
  "Empathy": "Empathy",
  "Wisdom tooth": "Wisdom teeth",
  "Tao Te Ching": "Tao Te Ching",
  "Value judgment": "Value judgement",
  "Solomon": "Solomon",
  "Fantasy": "Fantasy",
  "Ancient Greece": "Ancient Greece",
  "Library of Celsus": "Library of Celsus",
  "Taoism": "Taoism",
  "Snorri Sturluson": "Snorri Sturluson",
  "Islam": "Islam"
}