{
  "Turkey": "Туркия",
  "Caucasus": "Ккавкказ",
  "Czech Republic": "Чехия",
  "Russians": "Оьрус",
  "Avar language": "Яруссаннал маз",
  "Oak": "Пялут",
  "Malta": "Мальта",
  "Christianity": "Ххачпарас дин",
  "Lezgian language": "Лезгилал маз",
  "Slovakia": "Словакиа",
  "Caspian Sea": "Каспи хьхьири",
  "Turkish language": "Туркнал маз",
  "Europe": "Европа",
  "Latin": "ЛатӀин маз",
  "Istanbul": "Истамбул",
  "Gray wolf": "БарцӀ",
  "Moscow": "Москав",
  "Muslim": "Бусурман",
  "Bear": "Цуша",
  "Russia": "Аьрасат",
  "Ankara": "Анкъара",
  "Flag": "Ттугъ",
  "Georgia (country)": "Гуржисттан",
  "Birch": "КӀялагьи",
  "Olive": "Зайтун",
  "Black Sea": "ЛухӀи хьхьири",
  "Northern Cyprus": "Ухссавнил Кипр",
  "Chechen language": "Мичихичнал маз",
  "Netherlands": "Нидирланд",
  "Estonian language": "Эстон маз",
  "Denmark": "Дания",
  "South Ossetia": "Кьилвалул Осетия",
  "United States": "Американал ЦачӀунхьу Штатру",
  "Tbilisi": "Ттуплис",
  "Bulgaria": "Болгариа",
  "Romania": "Румыниа",
  "Estonians": "Эстон",
  "Noah": "НухӀ идавс",
  "Portugal": "Португал",
  "Kosovo": "Косова",
  "Azerbaijan": "Азирбижан",
  "Jesus": "Эса идавс",
  "Austria": "Австрия",
  "London": "Лондон",
  "Sea": "Хьхьири",
  "Pinophyta": "Ттарлил мурхь",
  "Islam": "Ислам"
}