{
  "Napolyon'un Rusya Seferi": "Campagne de Russie",
  "Louvre Müzesi": "Musée du Louvre",
  "Saint Helena": "Sainte-Hélène (île)",
  "André Tardieu": "André Tardieu",
  "Paris": "Paris",
  "Jean Casimir-Perier": "Jean Casimir-Perier",
  "Charles de Gaulle": "Charles de Gaulle",
  "Direktuvar": "Directoire",
  "Leipzig Muharebesi": "Bataille de Leipzig (1813)",
  "Le Sacre de Napoléon": "Le Sacre de Napoléon",
  "Paul Doumer": "Paul Doumer",
  "Albert Lebrun": "Albert Lebrun",
  "XII. Louis": "Louis XII",
  "Dördüncü Fransa Cumhuriyeti": "Quatrième République",
  "Vincent Auriol": "Vincent Auriol",
  "Alain Poher": "Alain Poher",
  "Şarlman": "Charlemagne",
  "I. Robert (Fransa)": "Robert Ier de France",
  "Ludwig van Beethoven": "Ludwig van Beethoven",
  "XV. Louis": "Louis XV",
  "Georges Bidault": "Georges Bidault",
  "Dazlak Karl": "Charles II le Chauve",
  "XVI. Louis": "Louis XVI",
  "Büyük Britanya ve İrlanda Birleşik Krallığı": "Royaume-Uni de Grande-Bretagne et d'Irlande",
  "XVII. Louis": "Louis XVII",
  "Viyana": "Vienne (Autriche)",
  "III. Napolyon": "Napoléon III",
  "Maurice Rouvier": "Maurice Rouvier",
  "Fransa Cumhuriyeti Geçici Hükümeti": "Gouvernement provisoire de la République française",
  "Manş Denizi": "Manche (mer)",
  "Osmanlı İmparatorluğu": "Empire ottoman",
  "VI. Louis": "Louis VI le Gros",
  "Napoli": "Naples",
  "Valois Hanedanı": "Maison capétienne de Valois",
  "Waterloo Muharebesi": "Bataille de Waterloo",
  "Jules Armand Dufaure": "Jules Dufaure",
  "Fransız Devrimi": "Révolution française",
  "Akka": "Acre (Israël)",
  "Kategori:Capet Hanedanı": "Catégorie:Capétien",
  "Şişman Karl": "Charles III le Gros",
  "İtalya Krallığı (1805-1814)": "Royaume d'Italie (1805-1814)",
  "Georges Pompidou": "Georges Pompidou",
  "Émile Loubet": "Émile Loubet",
  "Louis-Philippe": "Louis-Philippe Ier",
  "VII. Charles": "Charles VII (roi de France)",
  "Dindar Ludwig": "Louis le Pieux",
  "VI. Filip": "Philippe VI de Valois",
  "Raymond Poincaré": "Raymond Poincaré",
  "II. Henri (Fransa Kralı)": "Henri II (roi de France)",
  "Nicolas Sarkozy": "Nicolas Sarkozy",
  "Frédéric François-Marsal": "Frédéric François-Marsal",
  "Trafalgar Muharebesi": "Bataille de Trafalgar",
  "Ajaccio": "Ajaccio",
  "Uzak Doğu": "Extrême-Orient",
  "Alexandre Millerand": "Alexandre Millerand",
  "XIV. Louis": "Louis XIV",
  "İkinci Fransa Cumhuriyeti": "Deuxième République (France)",
  "V. Philippe (Fransa)": "Philippe V le Long",
  "Gaston Doumergue": "Gaston Doumergue",
  "Suriye": "Syrie",
  "VI. Charles": "Charles VI le Bien-Aimé",
  "VIII. Louis": "Louis VIII le Lion",
  "Jules Grévy": "Jules Grévy",
  "Vichy Fransası": "Régime de Vichy",
  "I. Aleksandr (Rusya)": "Alexandre Ier de Russie",
  "Fransa'nın Mısır Seferi": "Campagne d'Égypte",
  "Tilsit Antlaşmaları": "Traités de Tilsit",
  "Charles Dupuy": "Charles Dupuy",
  "Napolyon Bonapart": "Napoléon Ier",
  "François Hollande": "François Hollande",
  "Katolik Kilisesi": "Église catholique",
  "I. François (Fransa Kralı)": "François Ier (roi de France)",
  "Joséphine de Beauharnais": "Joséphine de Beauharnais",
  "Rusya İmparatorluğu": "Empire russe",
  "IX. Charles": "Charles IX (roi de France)",
  "Askerî darbe": "Coup d'État",
  "IV. Charles": "Charles IV le Bel",
  "Habsburg Hanedanı": "Habsbourg",
  "Patrice de Mac-Mahon": "Patrice de Mac Mahon",
  "VIII. Charles": "Charles VIII (roi de France)",
  "Birinci Fransa İmparatorluğu": "Premier Empire",
  "Jacques-Louis David": "Jacques-Louis David",
  "IV. Filip (Fransa)": "Philippe IV le Bel",
  "Orta Avrupa": "Europe centrale",
  "I. Filip (Fransa)": "Philippe Ier (roi des Francs)",
  "Philippe Pétain": "Philippe Pétain",
  "XVIII. Louis": "Louis XVIII",
  "II. François": "François II (roi de France)",
  "XI. Louis": "Louis XI",
  "Cezzar Ahmet Paşa": "Djezzar Pacha",
  "Mısır Eyaleti": "Province d'Égypte",
  "III. Henri (Fransa Kralı)": "Henri III (roi de France)",
  "XIII. Louis": "Louis XIII",
  "X. Charles": "Charles X (roi de France)",
  "Korsika": "Corse",
  "Fransızca": "Français",
  "II. Jean": "Jean II le Bon",
  "Notre Dame Katedrali": "Cathédrale Notre-Dame de Paris",
  "Borodino Muharebesi": "Bataille de la Moskova",
  "Paul Deschanel": "Paul Deschanel",
  "V. Charles (Fransa)": "Charles V le Sage",
  "General": "Général",
  "Félix Faure": "Félix Faure",
  "III. Filip (Fransa)": "Philippe III le Hardi",
  "Fransa": "France",
  "IX. Louis": "Louis IX",
  "Elba": "Île d'Elbe",
  "René Coty": "René Coty",
  "Bourbon Hanedanı": "Maison de Bourbon",
  "VII. Louis": "Louis VII le Jeune",
  "İsveç": "Suède",
  "Malta": "Malte",
  "Adolphe Thiers": "Adolphe Thiers",
  "Austerlitz Muharebesi": "Bataille d'Austerlitz",
  "Louis-Eugène Cavaignac": "Eugène Cavaignac (homme politique)",
  "Fransa cumhurbaşkanları listesi": "Liste des présidents de la République française",
  "Fontainebleau": "Fontainebleau",
  "Nil": "Nil",
  "Britanya İmparatorluğu": "Empire britannique",
  "Mihail Kutuzov": "Mikhaïl Koutouzov",
  "Valéry Giscard d'Estaing": "Valéry Giscard d'Estaing",
  "François Mitterrand": "François Mitterrand",
  "Yüz Gün": "Cent-Jours",
  "İskenderiye": "Alexandrie",
  "Armand Fallières": "Armand Fallières",
  "Üçüncü Fransa Cumhuriyeti": "Troisième République (France)",
  "Avusturya İmparatorluğu": "Empire d'Autriche",
  "Sadi Carnot (cumhurbaşkanı)": "Sadi Carnot (homme politique)",
  "Birinci Fransa Cumhuriyeti": "Première République (France)",
  "Les Invalides": "Hôtel des Invalides",
  "Charles Joseph Minard": "Charles Joseph Minard",
  "II. Filip (Fransa)": "Philippe II Auguste",
  "Léon Blum": "Léon Blum",
  "Ulusal Konvansiyon": "Convention nationale",
  "Fransa hükümdarları listesi": "Liste des monarques de France",
  "Beşinci Fransa Cumhuriyeti": "Cinquième République",
  "Horatio Nelson": "Horatio Nelson",
  "Moskova": "Moscou",
  "Jacques Chirac": "Jacques Chirac"
}