{
  "Pilietinis karas": "Civil war",
  "Įstatymas": "Law (principle)",
  "Prancūzija": "France",
  "Vikicitatos": "Wikiquote",
  "Policija": "Police",
  "Ministrų kabinetas": "Cabinet (government)",
  "Visuomenė": "Society",
  "Didžioji Prancūzijos revoliucija": "French Revolution",
  "Pažinimas": "Cognition",
  "Konfliktas": "Conflict (process)",
  "Gamta": "Nature",
  "Alexis de Tocqueville": "Alexis de Tocqueville",
  "Lotynų kalba": "Latin",
  "Kariuomenė": "Military",
  "Absoliutinė monarchija": "Absolute monarchy",
  "Politika": "Politics"
}