{
  "Aluschta": "Alushta",
  "Tschufut-Kale": "Chufut-Kale",
  "Asowsches Meer": "Sea of Azov",
  "Ermanarich": "Ermanaric",
  "Antike": "Classical antiquity",
  "Franklin D. Roosevelt": "Franklin D. Roosevelt",
  "Tabak": "Nicotiana",
  "Balaklawa": "Balaklava",
  "Mongolei": "Mongolia",
  "Osmanisches Reich": "Ottoman Empire",
  "Europa": "Europe",
  "Christentum": "Christianity",
  "Germanen": "Germanic peoples",
  "Kimmerier": "Cimmerians",
  "Judentum": "Judaism",
  "Jalta": "Yalta",
  "Byzantinisches Reich": "Byzantine Empire",
  "Josef Stalin": "Joseph Stalin",
  "Tataren": "Tatars",
  "Greuthungen": "Greuthungi",
  "Weizen": "Wheat",
  "Ukrainische Sprache": "Ukrainian language",
  "Sowjetunion": "Soviet Union",
  "Ukraine": "Ukraine",
  "Asien": "Asia",
  "Genua": "Genoa",
  "Mangup-Kale": "Mangup",
  "Zweiter Weltkrieg": "World War II",
  "Winston Churchill": "Winston Churchill",
  "Russische Sprache": "Russian language",
  "Chasaren": "Khazars",
  "Neandertaler": "Neanderthal",
  "Gemüse": "Vegetable",
  "Krimtatarische Sprache": "Crimean Tatar language",
  "Erster Weltkrieg": "World War I",
  "Römisches Reich": "Roman Empire",
  "Krimgoten": "Crimean Goths",
  "Altgriechische Sprache": "Ancient Greek",
  "Hunnen": "Huns",
  "Schwarzes Meer": "Black Sea",
  "Moskau": "Moscow",
  "Krimgebirge": "Crimean Mountains",
  "Russland": "Russia",
  "Sudak": "Sudak",
  "Taurer": "Tauri",
  "Islam": "Islam"
}