{
  "French Revolution": "फ्रेंच राज्यक्रांती",
  "Albert François Lebrun": "आल्बेर लेब्रन",
  "Cannon": "तोफ",
  "Seine": "सीन नदी",
  "Saint Helena": "सेंट हेलेना",
  "André Tardieu": "आंद्रे तार्द्यू",
  "François Mitterrand": "फ्रांस्वा मित्तराँ",
  "Second French Empire": "फ्रान्सचे दुसरे साम्राज्य",
  "Battle of Austerlitz": "ऑस्टर्लिट्झची लढाई",
  "Stomach cancer": "जठराचा कर्करोग",
  "Middle East": "मध्यपूर्व",
  "Horatio Nelson, 1st Viscount Nelson": "होरेशियो नेल्सन",
  "Vistula": "व्हिस्चुला नदी",
  "Louisiana": "लुईझियाना",
  "Gunboat War": "गनबोट युद्ध",
  "Battle of Eylau": "एयलाऊची लढाई",
  "Ludwig van Beethoven": "लुडविग फान बीथोव्हेन",
  "Louis XVI of France": "सोळावा लुई, फ्रान्स",
  "Electorate of Brunswick-Lüneburg": "ब्रुन्सविक-लूनबर्गचे निर्वाचन क्षेत्र",
  "Denmark–Norway": "डेन्मार्क-नॉर्वे",
  "Plato": "प्लेटो",
  "Liguria": "लिगुरिया",
  "Thomas Jefferson": "थॉमस जेफरसन",
  "Battle of Czarnowo": "झार्नोवोची लढाई",
  "Benjamin Franklin": "बेंजामिन फ्रँकलिन",
  "Spain": "स्पेन",
  "First French Empire": "फ्रान्सचे पहिले साम्राज्य",
  "Roman Empire": "रोमन साम्राज्य",
  "Franz Joseph I of Austria": "पहिला फ्रान्झ योजेफ, ऑस्ट्रिया",
  "Cádiz": "काडिस",
  "Charles de Gaulle": "चार्ल्स दि गॉल",
  "Dano-Swedish War of 1808–09": "१८०८-१८०९ चे डेन्मार्क-स्वीडन युद्ध",
  "Socrates": "सॉक्रेटिस",
  "Alexandria": "अलेक्झांड्रिया",
  "Russo-Turkish War (1806–12)": "रशिया-तुर्कस्तान युद्ध (१८०६-१८१२)",
  "Battle of Ligny": "लिग्नीची लढाई",
  "Francis II of France": "दुसरा फ्रांस्वा, फ्रान्स",
  "Hannibal": "हॅनिबल",
  "Battle of Issy": "इसीची लढाई",
  "French Fourth Republic": "चौथे फ्रेंच प्रजासत्ताक",
  "Battle of Wavre": "वाव्रची लढाई",
  "Kingdom of the Two Sicilies": "दोन सिसिलींचे राजतंत्र",
  "Jean-Jacques Rousseau": "ज्यां-जाक रूसो",
  "Artillery": "तोफखाना",
  "Adolf Hitler": "ॲडॉल्फ हिटलर",
  "Battle of Guttstadt-Deppen": "गुटश्टाट-डेपेनची लढाई",
  "Notre Dame de Paris": "नोत्र देम दे पॅरिस",
  "Imperial Guard (Napoleon I)": "शाही रक्षक (नेपोलियन बोनापार्ट)",
  "Pierre-Simon Laplace": "पिएर-सिमोन लाप्लास",
  "Félix Gouin": "फेलिक्स गोआं",
  "Guerrilla warfare": "गनिमी कावा",
  "William I, German Emperor": "विल्हेल्म पहिला, जर्मन सम्राट",
  "Cavalry": "घोडदळ",
  "Rhine": "र्‍हाइन नदी",
  "Henry II of France": "दुसरा हेन्री, फ्रान्स",
  "France": "फ्रान्स",
  "Louis XVII of France": "सतरावा लुई, फ्रान्स",
  "French invasion of Russia": "फ्रान्सचे रशियावरील आक्रमण",
  "Pope Pius VII": "पोप पायस सातवा",
  "Nicolas Sarkozy": "निकोला सार्कोझी",
  "William I of the Netherlands": "विल्यम पहिला, नेदरलँड्स",
  "Internet Movie Database": "इंटरनेट मुव्ही डेटाबेस",
  "French Third Republic": "तिसरे फ्रेंच प्रजासत्ताक",
  "Charles V, Holy Roman Emperor": "पहिला कार्लोस, स्पेन",
  "Vienna": "व्हियेना",
  "Bohemia": "बोहेमिया",
  "Francis II, Holy Roman Emperor": "फ्रांसिस दुसरा, पवित्र रोमन सम्राट",
  "Siege of Hameln": "हामेल्नचा वेढा",
  "Victor Emmanuel II of Italy": "दुसरा वित्तोरियो इमानुएले, इटली",
  "Battle of Jena–Auerstedt": "जेना-ऑर्स्टेडची लढाई",
  "Ajaccio": "अझाक्सियो",
  "Philip I of France": "पहिला फिलिप, फ्रान्स",
  "Félix Faure": "फेलिक्स फॉउ",
  "English Wars (Scandinavia)": "इंग्लिश युद्धे (स्कँडिनेव्हिया)",
  "Flag": "ध्वज",
  "Battle of Friedland": "फ्रीडलँडची लढाई",
  "Battle of Waterloo": "वॉटर्लूची लढाई",
  "Tuberculosis": "क्षय रोग",
  "Hundred Days": "शंभर दिवस",
  "Dominican Republic": "डॉमिनिकन प्रजासत्ताक",
  "Alexander the Great": "अलेक्झांडर द ग्रेट",
  "Grenoble": "ग्रेनोबल",
  "Antoine Lavoisier": "आँत्वान लेवॉइझिये",
  "Napoleon": "नेपोलियन बोनापार्ट",
  "Ferdinand VII of Spain": "फर्डिनांड सातवा, स्पेन",
  "Tuscany": "तोस्काना",
  "Salzburg": "जाल्त्सबुर्ग",
  "Louis IX of France": "नववा लुई, फ्रान्स",
  "Anglo-Turkish War (1807–09)": "इंग्लंड-तुर्कस्तान युद्ध (१८०७-१८०९)",
  "Metric system": "मेट्रिक पद्धती",
  "Jules Grévy": "जुल्स ग्रेव्ही",
  "Sweden": "स्वीडन",
  "Battle of Mohrungen": "मोहरुन्जेनची लढाई",
  "Haifa": "हैफा",
  "Henry III of France": "तिसरा हेन्री, फ्रान्स",
  "Charlemagne": "शार्लमेन",
  "Capitulation of Pasewalk": "पेसवॉकची शरणागती",
  "List of French monarchs": "फ्रान्सच्या राज्यकर्त्यांची यादी",
  "French Second Republic": "दुसरे फ्रेंच प्रजासत्ताक",
  "Napoleonic Wars": "नेपोलियोनिक युद्धे",
  "Battle of Prenzlau": "प्रेन्झ्लॉची लढाई",
  "Charles Dupuy": "चार्ल्स दुपॉय",
  "Louis XIV of France": "चौदावा लुई, फ्रान्स",
  "Charles IX of France": "नववा शार्ल, फ्रान्स",
  "Finnish War": "फिनलंडचे युद्ध",
  "Battle of Saalfeld": "साल्फेल्डची लढाई",
  "François Hollande": "फ्रांस्वा ऑलांद",
  "Brest, France": "ब्रेस्त",
  "United Kingdom of the Netherlands": "नेदरलँड्सचे संघटित राजतंत्र",
  "Ebro": "एब्रो नदी",
  "Quebec": "क्वेबेक",
  "Vichy France": "विशी फ्रान्स",
  "Danube": "डॅन्यूब नदी",
  "Legion of Honour": "लीजन ऑफ ऑनर",
  "Battle of Ronco": "रोन्कोची लढाई",
  "Louis the Pious": "भक्त लुई (पवित्र रोमन सम्राट)",
  "Louis XI of France": "अकरावा लुई, फ्रान्स",
  "Gaza City": "गाझा",
  "Greater Poland Uprising (1806)": "बृहत् पोलंडचा उठाव (१८०६)",
  "Voltaire": "व्होल्तेर",
  "Battle of Occhiobello": "ओकियोबेलोची लढाई",
  "Charles IV of France": "चौथा शार्ल, फ्रान्स",
  "Battle of Trafalgar": "ट्रफाल्गरची लढाई",
  "Champs-Élysées": "शाँज-एलिजे",
  "Syria": "सीरिया",
  "Elba": "एल्बा",
  "Louis XIII of France": "तेरावा लुई, फ्रान्स",
  "Battle of Rocheserviere": "रोशेसर्व्हियेरची लढाई",
  "Nice": "नीस",
  "Léon Blum": "लेओन ब्लुम",
  "Holy Roman Empire": "पवित्र रोमन साम्राज्य",
  "Louis XV of France": "पंधरावा लुई, फ्रान्स",
  "Francis I of France": "पहिला फ्रांस्वा, फ्रान्स",
  "Siege of Stralsund (1807)": "स्ट्रालसुंडचा वेढा (१८०७)",
  "Kingdom of Portugal": "पोर्तुगालचे राजतंत्र",
  "Battle of the Panaro": "पनारोची लढाई",
  "Haiti": "हैती",
  "Nature (journal)": "नेचर (जर्नल)",
  "Capitulation of Erfurt": "एर्फर्टची शरणागती",
  "Battle of Carpi (1815)": "कार्पीची लढाई (१८१५)",
  "Battle of Quatre Bras": "क्वात्रे ब्राची लढाई",
  "Franco-Swedish War": "नेपोलियनविरुद्धचे पहिले युद्ध",
  "English Channel": "इंग्लिश खाडी",
  "Poland": "पोलंड",
  "Republic of Venice": "व्हेनिसचे प्रजासत्ताक",
  "Battle of Heilsberg": "हाइल्सबर्गची लढाई",
  "Battle of Schleiz": "श्लाइझची लढाई",
  "Toulon": "तुलाँ",
  "Dos de Mayo Uprising": "दोन मेचा उठाव",
  "Ulm": "उल्म",
  "Francisco Goya": "फ्रांसिस्को गोया",
  "Louis XII of France": "बारावा लुई, फ्रान्स",
  "Battle of Golymin": "गोलिमिनची लढाई",
  "Adriatic Sea": "एड्रियाटिक समुद्र",
  "Kingdom of Great Britain": "ग्रेट ब्रिटनचे राजतंत्र",
  "Battle of Cesenatico": "केसेनातिकोची लढाई",
  "Arthur Wellesley, 1st Duke of Wellington": "आर्थर वेलेस्ली, ड्युक ऑफ वेलिंग्टन",
  "Russian Empire": "रशियन साम्राज्य",
  "Muhammad": "मोहम्मद पैगंबर",
  "Battle of Pułtusk": "पुल्तुस्कची लढाई",
  "Madrid": "माद्रिद",
  "Po (river)": "पो नदी",
  "Otto von Bismarck": "ओटो फॉन बिस्मार्क",
  "Caucasus": "कॉकेशस",
  "Louis XVIII of France": "अठरावा लुई, फ्रान्स",
  "Kingdom of Prussia": "प्रशियाचे राजतंत्र",
  "Charles VI of France": "सहावा शार्ल, फ्रान्स",
  "Siege of Magdeburg (1806)": "माक्देबुर्गचा वेढा (१८०६)",
  "Battle of Cannae": "कॅनेची लढाई",
  "Malta": "माल्टा",
  "Adolphe Thiers": "अॅडोल्फ तियेर",
  "Central Europe": "मध्य युरोप",
  "War of the Fourth Coalition": "चौथ्या संघाचे युद्ध",
  "Philip VI of France": "सहावा फिलिप, फ्रान्स",
  "War of the Third Coalition": "तिसर्‍या संघाचे युद्ध",
  "Lord Byron": "जॉर्ज गॉर्डन बायरन",
  "Austrian Empire": "ऑस्ट्रियन साम्राज्य",
  "Capitulation of Stettin": "स्तेतिनची शरणागती",
  "Philip V of France": "पाचवा फिलिप, फ्रान्स",
  "Portuguese Empire": "पोर्तुगीज साम्राज्य",
  "Valéry Giscard d'Estaing": "व्हॅलेरी जिस्कॅर देस्तें",
  "Napoleon III": "नेपोलियन तिसरा, फ्रान्स",
  "Charles the Bald": "टकल्या चार्ल्स",
  "Battle of La Suffel": "ला सफेलची लढाई",
  "Battle of Halle": "हॅलेची लढाई",
  "Montesquieu": "मॅान्टेस्क्यू",
  "Battle of Waren-Nossentin": "वारेन-नोसेन्तिनची लढाई",
  "Siege of Danzig (1807)": "डान्झिगचा वेढा (१८०७)",
  "Charles VIII of France": "आठवा शार्ल, फ्रान्स",
  "United States House of Representatives": "अमेरिकेच्या प्रतिनिधींचे सभागृह",
  "Jean-Auguste-Dominique Ingres": "ज्याँ ओगूस्ट डोमिनिक अँग्र",
  "Armand Fallières": "आर्मांड फॅलियेरेस",
  "Thomas Paine": "थॉमस पेन",
  "Henry IV of France": "चौथा हेन्‍री, फ्रान्स",
  "Tipu Sultan": "टिपू सुलतान",
  "House of Habsburg": "हाब्सबुर्ग राजघराणे",
  "Louis VII of France": "सातवा लुई, फ्रान्स",
  "Pope Pius VI": "पोप पायस सहावा",
  "Battle of Pesaro": "पेसारोची लढाई",
  "Ottoman Empire": "ओस्मानी साम्राज्य",
  "Spanish Empire": "स्पॅनिश साम्राज्य",
  "Battle of Rocquencourt": "रॉकेनकोर्टची लढाई",
  "Pyrenees": "पिरेनीज",
  "Alexander I of Russia": "पहिला अलेक्झांडर, रशिया",
  "Peninsular War": "द्वीपकल्पीय युद्ध",
  "Battle of Casaglia": "कासालिगाची लढाई",
  "Battle of Cabezón": "काबेझॉनची लढाई",
  "Guadeloupe": "ग्वादेलोप",
  "Catholic Church": "कॅथलिक चर्च",
  "Kingdom of Holland": "हॉलंडचे राजतंत्र",
  "Flag of France": "फ्रान्सचा ध्वज",
  "Charles VII of France": "सातवा शार्ल, फ्रान्स",
  "Siege of Kolberg (1807)": "कोलबर्गचा वेढा (१८०७)",
  "Tissue (biology)": "उती",
  "United Kingdom of Great Britain and Ireland": "ग्रेट ब्रिटन व आयर्लंडचे संयुक्त राजतंत्र",
  "Thomas Carlyle": "थॉमस कार्लाईल",
  "United Kingdom": "युनायटेड किंग्डम",
  "Dutch Republic": "डच प्रजासत्ताक",
  "Louvre": "लूव्र संग्रहालय",
  "Kingdom of Naples": "नेपल्सचे राजतंत्र",
  "Battle of Scapezzano": "स्कापेझानोची लढाई",
  "Georges Pompidou": "जोर्ज पाँपिदु",
  "French Guiana": "फ्रेंच गयाना",
  "Jacques Chirac": "जाक शिराक",
  "Holy Roman Emperor": "पवित्र रोमन सम्राट",
  "Liberalism": "उदारमतवाद",
  "Corsica": "कॉर्स"
}