{
  "1300": "1300",
  "Idioma ruso": "Russo",
  "Finlandia": "Finlandia",
  "Geografía": "Giugrafia",
  "Nicosia": "Nicosia",
  "Países Bajos": "Ulanna",
  "Latín": "Lengua latina",
  "Hungría": "Ungaria",
  "Oceanía": "Oceania",
  "Armenia": "Armenia",
  "1150": "1150",
  "Praga": "Praga",
  "Estados Unidos": "State Aunite d'Amereca",
  "Roma": "Romma",
  "Albania": "Albania",
  "Lenguas romances": "Lengue neolatine",
  "Bosnia y Herzegovina": "Bosnia-Erzegovina",
  "Organización de las Naciones Unidas": "Organizzazione d\"e Nazzione Aunite",
  "Rusia": "Russia",
  "OTAN": "NATO",
  "Idioma portugués": "Lengua purtuese",
  "París": "Parigge",
  "Unión Europea": "Aunione europea",
  "Bélgica": "Belge",
  "San Marino": "San Marino",
  "Azerbaiyán": "Azerbaijan",
  "Italia": "Italia",
  "Grecia": "Grecia",
  "Varsovia": "Varsavia",
  "1850": "1850",
  "Francia": "Franza",
  "Idioma italiano": "Lengua taliana",
  "Montenegro": "Montenegro",
  "Imperio romano": "Impero Rumano",
  "Idioma alemán": "Lengua germanese",
  "República Popular China": "Cina",
  "1400": "1400",
  "Siglo XVIII": "XVIII seculo",
  "Chipre": "Cipro",
  "Mar Tirreno": "Mar Tirreno",
  "Reino Unido": "Gran Vretagna",
  "Antigua Grecia": "Grecia antica",
  "Liechtenstein": "Liechtenstein",
  "Mar Adriático": "Mar Adriateco",
  "Capital (política)": "Capitale (città)",
  "Bulgaria": "Bulgaria",
  "Berlín": "Berlino",
  "Portugal": "Purtuallo",
  "Idioma sardo": "Lengua sarda",
  "Austria": "Austria",
  "Polonia": "Pulonnia",
  "Crimea": "Crimea",
  "Unión Soviética": "Aunione Sovieteca",
  "España": "Spagna",
  "Idioma inglés": "Lengua ngrese",
  "Política": "Politica",
  "Asia": "Asia",
  "Andorra": "Andorra",
  "Siglo XVI": "XVI seculo",
  "Moscú": "Mosca",
  "Mar Mediterráneo": "Mar Mediterraneo",
  "1900": "1900",
  "Vilna": "Vilnius",
  "Idioma siciliano": "Lengua siciliana",
  "Lenguas indoeuropeas": "Lengue innoeuropee",
  "Bucarest": "Bucarest",
  "Bielorrusia": "Bielorussia",
  "500 a. C.": "500 AC",
  "Idioma napolitano": "Lengua napulitana",
  "Primera Guerra Mundial": "Primma guerra munniale",
  "Océano Atlántico": "Oceano Atlanteco",
  "Georgia": "Georgia",
  "Idioma serbio": "Lengua serba",
  "América": "Amereca",
  "Noruega": "Norvegia",
  "Idioma polaco": "Lengua pulacca",
  "Siglo XVII": "XVII seculo",
  "1991": "1991",
  "Turquía": "Turchia",
  "1995": "1995",
  "1994": "1994",
  "Estonia": "Estonia",
  "Bruselas": "Bruxelles",
  "Suiza": "Sguizzera",
  "Atenas": "Atene",
  "Dinamarca": "Danemarca",
  "Ámsterdam": "Amsterdam",
  "Judaísmo": "Giurieismo",
  "Euro": "Euro",
  "28 de abril": "28 'e abbrile",
  "Transnistria": "Transnistria",
  "África": "Africa",
  "Idioma español": "Lengua spagnuola",
  "Berna": "Berna",
  "Idioma croata": "Lengua cruata",
  "Copenhague": "Copenaghen",
  "San Marino (ciudad)": "Cità 'e San Marino",
  "Continente": "Cuntinente",
  "Alemania": "Germania",
  "Suecia": "Sguezia",
  "1750": "1750",
  "Vaduz": "Vaduz",
  "2005": "2005",
  "Ciudad del Vaticano": "Cità d''o Vaticano",
  "Minsk": "Minsk",
  "Sarajevo": "Sarajevo",
  "República Checa": "Repubbreca Ceca",
  "Ucrania": "Ucraina",
  "Idioma francés": "Lengua franzese",
  "1800": "1800",
  "Serbia": "Serbia",
  "Sol": "Sole",
  "Londres": "Londra",
  "Rumania": "Rumania",
  "Edad Media": "Medioevo",
  "Segunda Guerra Mundial": "Siconda guerra munniale",
  "Península balcánica": "Balcane",
  "2007": "2007",
  "2004": "2004",
  "Lituania": "Lituania",
  "2008": "2008",
  "Croacia": "Croazia",
  "Islam": "Islam"
}