{
  "1804. gads": "1804",
  "Vaterlo kauja": "Schlacht bei Waterloo",
  "1814. gads": "1814",
  "1805. gads": "1805",
  "Viktors Emanuels II": "Viktor Emanuel II.",
  "Kārlis V Habsburgs": "Karl V. (HRR)",
  "Itālija": "Italien",
  "Kaļiņingradas apgabals": "Oblast Kaliningrad",
  "Vēsture": "Geschichte",
  "Senās Romas imperatori": "Liste der römischen Kaiser der Antike",
  "Krievija": "Russland",
  "Apvienotā Karaliste": "Vereinigtes Königreich",
  "Itālijas karaliste": "Königreich Italien",
  "Elba (sala)": "Elba",
  "Beļģija": "Belgien",
  "20. marts": "20. März",
  "Francijas Pirmā impērija": "Französisches Kaiserreich",
  "Austerlicas kauja": "Schlacht bei Austerlitz",
  "Leipciga": "Leipzig",
  "Kongresa bibliotēka": "Library of Congress",
  "Ažaksjo": "Ajaccio",
  "1821. gads": "1821",
  "Luijs XVIII": "Ludwig XVIII.",
  "Ēģipte": "Ägypten",
  "Francija": "Frankreich",
  "Valsts apvērsums": "Putsch",
  "15. augusts": "15. August",
  "Korsika": "Korsika",
  "Vikikrātuve": "Wikimedia Commons",
  "Austrijas Marija Luīze": "Marie-Louise von Österreich",
  "Svētās Helēnas Sala": "St. Helena (Insel)",
  "Prūsija": "Preußen",
  "1812. gada karš": "Russlandfeldzug 1812",
  "Autoritatīvā vadība": "Normdatei",
  "Austrālijas Nacionālā bibliotēka": "National Library of Australia",
  "22. jūnijs": "22. Juni",
  "Franču valoda": "Französische Sprache",
  "1. marts": "1. März",
  "Čehija": "Tschechien",
  "6. aprīlis": "6. April",
  "Vācija": "Deutschland",
  "1769. gads": "1769",
  "Franču revolūcija": "Französische Revolution",
  "1815. gads": "1815",
  "Imperators": "Kaiser",
  "5. maijs": "5. Mai",
  "Virtuālā starptautiskā autoritatīvā datne": "Virtual International Authority File",
  "Napoleons II": "Napoleon Franz Bonaparte"
}